teppan/__init__.py
teppan-0.2a1.dist-info/WHEEL
teppan-0.2a1.dist-info/METADATA
teppan-0.2a1.dist-info/RECORD
